MANIFEST.in
setup.py
egopowerflow/__init__.py
egopowerflow.egg-info/PKG-INFO
egopowerflow.egg-info/SOURCES.txt
egopowerflow.egg-info/dependency_links.txt
egopowerflow.egg-info/requires.txt
egopowerflow.egg-info/top_level.txt
egopowerflow/examples/__init__.py
egopowerflow/examples/mv_grid.py
egopowerflow/tools/__init__.py
egopowerflow/tools/config.json
egopowerflow/tools/io.py
egopowerflow/tools/plot.py
egopowerflow/tools/tools.py