Metadata-Version: 1.0
Name: egopowerflow
Version: 0.0.5
Summary: Powerflow analysis based on PyPSA
Home-page: UNKNOWN
Author: openego development group
Author-email: oemof@rl-institut.de
License: GNU Affero General Public License Version 3 (AGPL-3.0)
Platform: UNKNOWN
